wtypes/__init__.py
wtypes/base.py
wtypes/combining_types.py
wtypes/conf.py
wtypes/content_types.py
wtypes/dataclass.py
wtypes/evented.py
wtypes/examples.py
wtypes/python_types.py
wtypes/rdf.py
wtypes/spec.py
wtypes/string_formats.py
wtypes/utils.py
wtypes/tests/test_examples.ipynb
wtypes/tests/test_wtypes.ipynb
wtypes/widgets/__init__.py
wtypes/widgets/ipywidgets.py
wtypes-0.0.2.dist-info/LICENSE
wtypes-0.0.2.dist-info/WHEEL
wtypes-0.0.2.dist-info/METADATA
wtypes-0.0.2.dist-info/RECORD
