Metadata-Version: 2.1
Name: wtypes
Version: 0.0.2
Summary: extended python types for the web and json
Home-page: https://github.com/deathbeds/wtypes
License: BSD-3-Clause
Keywords: 
Author: deathbeds
Author-email: tony.fast@gmail.com
Requires-Dist: jsonschema
Requires-Dist: munch
Requires-Dist: anyconfig
Requires-Dist: pluggy
Requires-Dist: hypothesis-jsonschema ; extra == "examples"
Requires-Dist: genson ; extra == "examples"
Requires-Dist: param ; extra == "widgets"
Requires-Dist: ipywidgets ; extra == "widgets"
Provides-Extra: examples
Provides-Extra: widgets
